{
    "Title": "EZVisual",
    "FPS": 40,
    "Background": "#000000",
    "Layout": {
        "Type": "StackView",
        "Orientation": "Horizontal",
        "Background": {
            "BrushType" : "LinearGradientBrush",
            "ColorFrames" : [
                "#000000",
                "#456789",
                "#789ABC"
            ],
            "OffsetFrames" : [
                0, 0.6, 1
            ],
            "Angle" : 60
        },
        "Children": [
            {
                "Type": "StackView",
                "Orientation": "Vertical",
                "Padding": 20,
                "Children":[
                    {   "Type": "PlainText",
                        "Text": "EZVisual",
                        "FontColor": "#ffffff",
                        "FontSize": 1.6,
                        "FontWeight": 2    },

                    {   "Type": "PlainText",
                        "Text": "Demo",
                        "Margin" : [0, 0, 0, 16],
                        "FontColor": "#ffffff",
                        "FontSize": 1,
                        "FontWeight": 2    },

                    {   "Type": "Border", "Id": 0,
                        "Height": 40, "Width": 160,
                        "Background": "#ffffffff",
                        "Margin" : [0, 0, 0, 4],
                        "Padding": 2,
                        "Content":{
                            "Type": "Border",
                            "Id": 10,
                            "Width": "FillParent", "Height": "FillParent",
                            "Background": "#ff0000"
                        }},

                    {   "Type": "Border", "Id": 1,
                        "Height": 40, "Width": 160,
                        "Background": "#00000000",
                        "Margin" : [0, 0, 0, 4],
                        "Padding": 2,
                        "Content":{
                            "Type": "Border",
                            "Id": 11, "Width":
                            "FillParent", "Height": "FillParent",
                            "Background": "#ffb11b"
                        }},

                    {   "Type": "Border", "Id": 2,
                        "Height": 40, "Width": 160,
                        "Background": "#00000000",
                        "Margin" : [0, 0, 0, 4],
                        "Padding": 2,
                        "Content":{
                            "Type": "Border",
                            "Id": 12,
                            "Width": "FillParent", "Height": "FillParent",
                            "Background": "#f596aa"
                        }},

                    {   "Type": "Border", "Id": 3,
                        "Height": 40, "Width": 160,
                        "Background": "#00000000",
                        "Margin" : [0, 0, 0, 4],
                        "Padding": 2,
                        "Content":{
                            "Type": "Border",
                            "Id": 13,
                            "Width": "FillParent", "Height": "FillParent",
                            "Background": "#58b2dc"
                        }},

                    {   "Type": "PlainText",
                        "Text": "Github@MilesChing",
                        "Margin" : [0, 20, 0, 0],
                        "FontColor": "#FFFFFF",
                        "FontSize": 0.6,
                        "FontWeight": 1,
                        "FontFamily": 2     }
                ]
            },

            {
                "Type": "Border",
                "Padding": 1,
                "Margin": [0, 20, 20, 20],
                "Content":{
                    "Type": "Canvas", "Id": 16,
                    "LayerHeight": 400,
                    "LayerWidth": 400,
                    "Background": "#77000000",
                    "LayerCount": 5
                }
            }
        ]
    }
}